README.md
setup.py
Base/AdbCommon.py
Base/BaseAnalysis.py
Base/BaseCashEmnu.py
Base/BaseFile.py
Base/BaseMonitor.py
Base/BaseMonkeyConfig.py
Base/BasePhoneMsg.py
Base/BasePickle.py
Base/BaseReport.py
Base/BaseWriteReport.py
Base/Cprint.py
Base/OperateFile.py
Base/__init__.py
Base/monkeyTest.py
jiujiTestTool.egg-info/PKG-INFO
jiujiTestTool.egg-info/SOURCES.txt
jiujiTestTool.egg-info/dependency_links.txt
jiujiTestTool.egg-info/top_level.txt