Metadata-Version: 1.0
Name: jiujiTestTool
Version: 4.0
Summary: a library for jiujiTool Developer
Home-page: https://github.com/lol666666/jiujiTool.git
Author: lol666666
Author-email: loveworkyeah@163.com
License: MIT License
Keywords: jiujiTestTool
Platform: any
